cjkcms/__init__.py
cjkcms/apps.py
cjkcms/fields.py
cjkcms/forms.py
cjkcms/image_formats.py
cjkcms/search_urls.py
cjkcms/settings.py
cjkcms/urls.py
cjkcms/views.py
cjkcms/wagtail_hooks.py
cjkcms/widgets.py
cjkcms/api/__init__.py
cjkcms/api/mailchimp.py
cjkcms/bin/__init__.py
cjkcms/bin/cjkcms.py
cjkcms/blocks/__init__.py
cjkcms/blocks/base_blocks.py
cjkcms/blocks/content_blocks.py
cjkcms/blocks/html_blocks.py
cjkcms/blocks/layout_blocks.py
cjkcms/blocks/searchable_html_block.py
cjkcms/blocks/content/__init__.py
cjkcms/blocks/content/countdown.py
cjkcms/blocks/content/events.py
cjkcms/blocks/content/multistep.py
cjkcms/blocks/content/steps.py
cjkcms/draftail/__init__.py
cjkcms/draftail/draftail_extensions.py
cjkcms/finders/__init__.py
cjkcms/finders/oembed.py
cjkcms/management/commands/__init__.py
cjkcms/management/commands/clear-embeds.py
cjkcms/management/commands/import-csv.py
cjkcms/management/commands/init-collections.py
cjkcms/management/commands/init-navbar.py
cjkcms/management/commands/init-website.py
cjkcms/migrations/0001_initial.py
cjkcms/migrations/0002_alter_body_to_cjkcmsstreamfield.py
cjkcms/migrations/0003_alter_footer_content_alter_navbar_menu_items.py
cjkcms/migrations/0004_layoutsettings_articles_date_format_and_more.py
cjkcms/migrations/0005_layoutsettings_custom_font_and_more.py
cjkcms/migrations/0006_analyticssettings_consent_modal_layout_and_more.py
cjkcms/migrations/0007_layoutsettings_bootstrap_icons.py
cjkcms/migrations/0008_alter_layoutsettings_navbar_langselector.py
cjkcms/migrations/0009_navbar_language.py
cjkcms/migrations/0010_filmstrip_filmpanel.py
cjkcms/migrations/0011_cjkcmspage_related_classifier_term_and_more.py
cjkcms/migrations/0012_remove_analyticssettings_ga_tracking_id_and_more.py
cjkcms/migrations/0013_socialmediasettings_location.py
cjkcms/migrations/0014_navbar_alignment.py
cjkcms/migrations/0015_eventcalendar.py
cjkcms/migrations/0016_layoutsettings_breadcrumb_icon_and_more.py
wagtail_cjkcms-25.12.3.dist-info/licenses/LICENSE
wagtail_cjkcms-25.12.3.dist-info/METADATA
wagtail_cjkcms-25.12.3.dist-info/WHEEL
wagtail_cjkcms-25.12.3.dist-info/entry_points.txt
wagtail_cjkcms-25.12.3.dist-info/top_level.txt
wagtail_cjkcms-25.12.3.dist-info/RECORD
