Metadata-Version: 2.4
Name: wagtail-cjkcms
Version: 25.12.3
Summary: Wagtail Content Management System, installable as a Django app into any Wagtail 4.1.x/5.x/6.x site.
Author-email: Grzegorz Krol <gk@cjk.pl>
License: BSD-3-Clause
Project-URL: Homepage, https://cjkcms.com
Project-URL: Repository, https://github.com/cjkpl/wagtail-cjkcms
Keywords: wagtail,django,cms
Classifier: Environment :: Web Environment
Classifier: Framework :: Django
Classifier: Framework :: Django :: 4.1
Classifier: Framework :: Django :: 4.2
Classifier: Framework :: Wagtail :: 4
Classifier: Framework :: Wagtail :: 5
Classifier: Framework :: Wagtail :: 6
Classifier: Intended Audience :: Developers
Classifier: License :: OSI Approved :: BSD License
Classifier: Operating System :: OS Independent
Classifier: Programming Language :: Python
Classifier: Programming Language :: Python :: 3
Classifier: Programming Language :: Python :: 3 :: Only
Classifier: Programming Language :: Python :: 3.9
Classifier: Programming Language :: Python :: 3.10
Classifier: Programming Language :: Python :: 3.11
Classifier: Programming Language :: Python :: 3.12
Classifier: Topic :: Internet :: WWW/HTTP
Classifier: Topic :: Internet :: WWW/HTTP :: Site Management
Requires-Python: >=3.9
License-File: LICENSE
Requires-Dist: django-bootstrap5
Requires-Dist: django>=5.0
Requires-Dist: wagtail>=6.0
Requires-Dist: wagtail-seo>=3.0
Requires-Dist: wagtail-cache>=2.5.1
Requires-Dist: wagtail-color-panel
Dynamic: license-file
